setup.py
Animapy.egg-info/PKG-INFO
Animapy.egg-info/SOURCES.txt
Animapy.egg-info/dependency_links.txt
Animapy.egg-info/requires.txt
Animapy.egg-info/top_level.txt
animapy/__init__.py
animapy/helpers/__init__.py
animapy/helpers/common.py
animapy/sources/__init__.py
animapy/sources/anitube.py
animapy/sources/nwanime.py